qiskit_aqua_interfaces/VERSION.txt
qiskit_aqua_interfaces/__init__.py
qiskit_aqua_interfaces/_extras_require.py
qiskit_aqua_interfaces/version.py
qiskit_aqua_interfaces/aqua/__init__.py
qiskit_aqua_interfaces/aqua/browser/__init__.py
qiskit_aqua_interfaces/aqua/browser/__main__.py
qiskit_aqua_interfaces/aqua/browser/_controller.py
qiskit_aqua_interfaces/aqua/browser/_emptyview.py
qiskit_aqua_interfaces/aqua/browser/_mainview.py
qiskit_aqua_interfaces/aqua/browser/_model.py
qiskit_aqua_interfaces/aqua/browser/_scrollbarview.py
qiskit_aqua_interfaces/aqua/browser/_sectionpropertiesview.py
qiskit_aqua_interfaces/aqua/browser/_sectionsview.py
qiskit_aqua_interfaces/aqua/browser/command_line.py
qiskit_aqua_interfaces/aqua/command_line/__init__.py
qiskit_aqua_interfaces/aqua/command_line/__main__.py
qiskit_aqua_interfaces/aqua/command_line/command_line.py
qiskit_aqua_interfaces/aqua/user_interface/__init__.py
qiskit_aqua_interfaces/aqua/user_interface/__main__.py
qiskit_aqua_interfaces/aqua/user_interface/_aquaguiprovider.py
qiskit_aqua_interfaces/aqua/user_interface/_aquathread.py
qiskit_aqua_interfaces/aqua/user_interface/_controller.py
qiskit_aqua_interfaces/aqua/user_interface/_model.py
qiskit_aqua_interfaces/aqua/user_interface/_uipreferences.py
qiskit_aqua_interfaces/aqua/user_interface/command_line.py
qiskit_aqua_interfaces/aqua/user_interface/input_template.json
qiskit_aqua_interfaces/chemistry/__init__.py
qiskit_aqua_interfaces/chemistry/command_line/__init__.py
qiskit_aqua_interfaces/chemistry/command_line/__main__.py
qiskit_aqua_interfaces/chemistry/command_line/command_line.py
qiskit_aqua_interfaces/chemistry/user_interface/__init__.py
qiskit_aqua_interfaces/chemistry/user_interface/__main__.py
qiskit_aqua_interfaces/chemistry/user_interface/_chemguiprovider.py
qiskit_aqua_interfaces/chemistry/user_interface/_chemsectionpropertiesview.py
qiskit_aqua_interfaces/chemistry/user_interface/_chemthread.py
qiskit_aqua_interfaces-0.2.1.dist-info/LICENSE.txt
qiskit_aqua_interfaces-0.2.1.dist-info/METADATA
qiskit_aqua_interfaces-0.2.1.dist-info/WHEEL
qiskit_aqua_interfaces-0.2.1.dist-info/entry_points.txt
qiskit_aqua_interfaces-0.2.1.dist-info/top_level.txt
qiskit_aqua_interfaces-0.2.1.dist-info/RECORD
