Metadata-Version: 2.1
Name: qiskit-aqua-interfaces
Version: 0.2.1
Summary: Qiskit Aqua Interfaces
Home-page: https://github.com/Qiskit/qiskit_aqua_interfaces
Author: Qiskit Aqua Development Team
Author-email: qiskit@us.ibm.com
License: Apache-2.0
Keywords: qiskit sdk quantum aqua
Platform: UNKNOWN
Classifier: Environment :: Console
Classifier: License :: OSI Approved :: Apache Software License
Classifier: Intended Audience :: Developers
Classifier: Intended Audience :: Science/Research
Classifier: Operating System :: Microsoft :: Windows
Classifier: Operating System :: MacOS
Classifier: Operating System :: POSIX :: Linux
Classifier: Programming Language :: Python :: 3.5
Classifier: Programming Language :: Python :: 3.6
Classifier: Programming Language :: Python :: 3.7
Classifier: Topic :: Scientific/Engineering
Requires-Python: >=3.5
Requires-Dist: qiskit-aqua (<0.7.0,>=0.6.0)
Requires-Dist: pyobjc-core ; sys_platform == "darwin"
Requires-Dist: pyobjc-framework-Cocoa ; sys_platform == "darwin"
